{
    "key": "sociodemographic-data-vih",
    "form": "[{'type':'title','name':'Datos sociodemográficos'},{'type':'select','name':'phenotype','label':'Fenotipo','disabled':false,'placeholder':'','options':[{'name':'Caucásico', 'value':'Caucásico'},{'name':'Latinoamericano', 'value':'Latinoamericano'},{'name':'Asiático', 'value':'Asiático'},{'name':'Africano (raza negra)', 'value':'Africano (raza negra)'},{'name':'Otros', 'value':'Otros'}]},{'type':'input','name':'anotherPhenotype','label':'Otros fenotipos','disabled':true, 'enableWhen':['phenotype','Otros']},{'type':'select','name':'infectionVia','label':'Vía de infecciones (antiguo Grupo de riesgo)','disabled':false,'placeholder':'','options':[{'name':'Heterosexual', 'value':'Heterosexual'},{'name':'Homosexual / bisexual', 'value':'Homosexual / bisexual'},{'name':'Transmisión vertical', 'value':'Transmisión vertical'},{'name':'A.D.V.P.', 'value':'A.D.V.P.'},{'name':'Transfusion', 'value':'Transfusion'}, {'name':'Desconocido', 'value':'Desconocido'},{'name':'Otro', 'value':'Otro'}]},{'type':'input','label':'Actividad laboral','name':'laboralActivity', 'calculated_back':true,'disabled':false,'placeholder':'Actividad Laboral'},{'type':'input','label':'Clasificación ISCO','name':'isco', 'disabled':false,'placeholder':'Clasificación ISCO'},{'type':'input','label':'Clasificación NACE','name':'nace', 'disabled':false,'placeholder':'Clasificación NACE'},{'type':'select','name':'studiesLevelSelect','label':'Nivel de estudios','disabled':false,'placeholder':'','options':[{'name':'Sin estudios', 'value':'Sin estudios'}, {'name':'Primaria', 'value':'Primaria'}, {'name':'Secundaria', 'value':'Secundaria'}, {'name':'Universitaria', 'value':'Universitaria'}]},{'type':'input','label':'Años de educación','name':'educationYears', 'disabled':false,'placeholder':'Años de educación','validation':'Validators.pattern([0-9]*),Validators.maxLength(2)'}]",
    "buttons": "['save','clean']",
    "historify": false,
    "nameHistoricalDate": null,
    "fieldsToGraph": null
}