{
    "key": "consent",
    "form": "[{'type':'title','name':'CONSENTIMIENTO'},{'name':'accordion-example','type':'accordion','accordion':{'panels':[{'header':'Herramientas Hopes','content':[{'type':'section','name':'Consentimiento'},{'type':'checkbox','name':'patientConsent','css':'col-12 col-sm-12 col-md-6 col-lg-6 col-xl-6','label':'Consentimiento del paciente','disabled':false,'placeholder':''},{'type':'checkbox','name':'representativeConsent','css':'col-12 col-sm-12 col-md-6 col-lg-6 col-xl-6','label':'Consentimiento del representante','disabled':false,'placeholder':''},{'type':'section','name':'Conformidad'},{'type':'checkbox','name':'ordinarityConformity','css':'col-12 col-sm-12 col-md-6 col-lg-6 col-xl-6','label':'Conformidad de carácter ordinario','disabled':false,'placeholder':''},{'type':'checkbox','name':'specialConformity','css':'col-12 col-sm-12 col-md-6 col-lg-6 col-xl-6','label':'Conformidad de carácter especial','disabled':false,'placeholder':''}]},{'header':'Aplicación de Fotos','content':[{'type':'text','name':'textspace','value':'Se preservará la confidencialidad de sus datos personales. En caso de necesitar utilizar imágenes suyas con fines médicos/científicos, serán debidamente modificadas para evitar que pueda ser reconocido. Las nuevas tecnologías permiten el envío de imágenes a través de internet de forma cifrada, impidiendo que personas no autorizadas pudieran abrirlas'},{'type':'section','name':'pictures','value':'¿Consiente usted la realización de fotos de las lesiones para la monitorización de su enfermedad?'},{'type':'checkbox','name':'picturesPatientConsent','css':'col-12 col-sm-12 col-md-6 col-lg-6 col-xl-6','label':'Consentimiento del paciente','disabled':false,'placeholder':''},{'type':'checkbox','name':'picturesRepresentativeConsent','css':'col-12 col-sm-12 col-md-6 col-lg-6 col-xl-6','label':'Consentimiento del representante','disabled':false,'placeholder':''},{'type':'section','name':'picturePublishing','value':'¿Consiente usted que las fotos de las lesiones puedan ser utilizadas con fines docentes, publicaciones médicas o divulgación sanitaria?'},{'type':'checkbox','name':'picturePublishingPatientConsent','css':'col-12 col-sm-12 col-md-6 col-lg-6 col-xl-6','label':'Consentimiento del paciente','disabled':false,'placeholder':''},{'type':'checkbox','name':'picturePublishingRepresentativeConsent','css':'col-12 col-sm-12 col-md-6 col-lg-6 col-xl-6','label':'Consentimiento del representante','disabled':false,'placeholder':''}]}]}}]",
    "buttons": "['save']",
    "historify": false,
    "isTable": null,
    "nameHistoricalDate": null,
    "fieldsToGraph": null
}